pythercis
