Metadata-Version: 1.0
Name: pythercis
Version: 0.1.1
Summary: Python bindings for EtherCIS
Home-page: https://github.com/Epidurio/pythercis
Author: Dr Marcus Baw
Author-email: marcusbaw@gmail.com
License: MIT
Platform: UNKNOWN
